Tests/__init__.py
Tests/test_pytest.py
g4s/__init__.py
g4s/alarm.py
g4s/utils/__init__.py
g4s/utils/alarm_status.py
g4s/utils/api.py
g4s/utils/enums.py
g4s/utils/panel_settings.py
g4s/utils/panel_state.py
g4s/utils/state_device.py
g4s/utils/static_utils.py
g4s/utils/time_zone.py
g4s/utils/user.py
G4S-1.0.8.dist-info/METADATA
G4S-1.0.8.dist-info/WHEEL
G4S-1.0.8.dist-info/top_level.txt
G4S-1.0.8.dist-info/RECORD
