Metadata-Version: 2.1
Name: G4S
Version: 1.0.8
Summary: API interface for G4S Alarms
Home-page: https://github.com/PTST/G4S_Alarm_Py
Author: PTST
Author-email: patrick@steffensen.io
License: UNKNOWN
Platform: UNKNOWN
Classifier: Programming Language :: Python :: 3
Classifier: License :: OSI Approved :: MIT License
Classifier: Operating System :: OS Independent
Requires-Python: >=3.8
Requires-Dist: requests (>=2.23.0)
Requires-Dist: python-dateutil (>=2.8.1)
